duckdi/__init__.py
duckdi/cli.py
duckdi/errors/__init__.py
duckdi/errors/adapter_already_registered_error.py
duckdi/errors/interface_already_registered.py
duckdi/errors/invalid_adapter_implementation_error.py
duckdi/errors/missing_injection_payload_error.py
duckdi/modules/get.py
duckdi/modules/injections_container.py
duckdi/modules/injections_payload.py
duckdi/modules/interface.py
duckdi/modules/register.py
duckdi/utils/__init__.py
duckdi/utils/buffer_readers.py
duckdi/utils/serializers.py
duckdi-0.1.13.dist-info/METADATA
duckdi-0.1.13.dist-info/WHEEL
duckdi-0.1.13.dist-info/entry_points.txt
duckdi-0.1.13.dist-info/RECORD
