Metadata-Version: 2.3
Name: duckdi
Version: 0.1.13
Summary: 🦆 A minimal dependency injection library for Python
License: MIT
Author: Phe Pato
Author-email: pheprogrammer@gmail.com
Requires-Python: >=3.10
Classifier: License :: OSI Approved :: MIT License
Classifier: Programming Language :: Python :: 3
Classifier: Programming Language :: Python :: 3.10
Classifier: Programming Language :: Python :: 3.11
Classifier: Programming Language :: Python :: 3.12
Classifier: Programming Language :: Python :: 3.13
Requires-Dist: toml (>=0.10.2,<0.11.0)
Project-URL: Homepage, https://pypi.org/project/duckdi/
Project-URL: Repository, https://github.com/PheFreire/DuckDI
